LICENSE
MANIFEST.in
README.md
setup.py
pyformance/__init__.py
pyformance/__version__.py
pyformance/registry.py
pyformance.egg-info/PKG-INFO
pyformance.egg-info/SOURCES.txt
pyformance.egg-info/dependency_links.txt
pyformance.egg-info/requires.txt
pyformance.egg-info/top_level.txt
pyformance/meters/__init__.py
pyformance/meters/counter.py
pyformance/meters/gauge.py
pyformance/meters/histogram.py
pyformance/meters/meter.py
pyformance/meters/timer.py
pyformance/reporters/__init__.py
pyformance/reporters/carbon_reporter.py
pyformance/reporters/console_reporter.py
pyformance/reporters/csv_reporter.py
pyformance/reporters/hosted_graphite_reporter.py
pyformance/reporters/influx.py
pyformance/reporters/newrelic_reporter.py
pyformance/reporters/opentsdb_reporter.py
pyformance/reporters/reporter.py
pyformance/reporters/syslog_reporter.py
pyformance/stats/__init__.py
pyformance/stats/moving_average.py
pyformance/stats/samples.py
pyformance/stats/snapshot.py
tests/__init__.py
tests/test__carbon_reporter.py
tests/test__console_reporter.py
tests/test__counter.py
tests/test__csv_reporter.py
tests/test__gauge.py
tests/test__histogram.py
tests/test__influx_reporter.py
tests/test__meter.py
tests/test__moving_average.py
tests/test__newrelic_reporter.py
tests/test__opentsdb_reporter.py
tests/test__registry.py
tests/test__syslog_reporter.py
tests/test__timer.py